synple/__init__.py
synple/synple.py
synple/data/CIA.H2H2.Yi
synple/data/CIA_H2H.dat
synple/data/CIA_H2H2.dat
synple/data/CIA_H2He.dat
synple/data/CIA_HHe.dat
synple/data/Ca1kas_F_zat.sy
synple/data/Ca2kas_F_zat.sy
synple/data/KIkas.tl
synple/data/Mg1kas_F_ccc.sy
synple/data/Mg2kas_F_ccc.sy
synple/data/NaIkas.tl
synple/data/al1.t
synple/data/al2.t
synple/data/al2_20+9lev.dat
synple/data/al3_19+4lev.dat
synple/data/al4hyd.dat
synple/data/al5hyd.dat
synple/data/ar1_71lev-jK.dat
synple/data/ar2_42+12lev.dat
synple/data/ar3_27+17lev.dat
synple/data/ar4_25+11lev.dat
synple/data/b1.t
synple/data/b2.t
synple/data/be1.t
synple/data/be2.t
synple/data/c1.dat
synple/data/c1.t
synple/data/c2.dat
synple/data/c2.t
synple/data/c3_34+12lev.dat
synple/data/c4.dat
synple/data/ca1.t
synple/data/ca2.t
synple/data/f1.t
synple/data/f2.t
synple/data/fe1.dat
synple/data/fe2p_14+11lev.rap
synple/data/fe2va.dat
synple/data/fe3p_22+7lev.rap
synple/data/fe3va.dat
synple/data/fe4p_21+11lev.rap
synple/data/fe4va.dat
synple/data/fe5p_19+11lev.rap
synple/data/fe5va.dat
synple/data/fe6b.rap
synple/data/fe6v.dat
synple/data/fe7.dat
synple/data/fe7.rap
synple/data/h1.dat
synple/data/h1_16lev2.dat
synple/data/h1s.dat
synple/data/h1s16.dat
synple/data/h2o_exomol.pf
synple/data/he1.dat
synple/data/he1.t
synple/data/he1prf.dat
synple/data/he2.dat
synple/data/he2prf.dat
synple/data/hm.dat
synple/data/hydprf.dat
synple/data/irwin.dat
synple/data/irwin_bc.dat
synple/data/irwin_orig.dat
synple/data/laquasi.dat
synple/data/lbquasi.dat
synple/data/lemke.dat
synple/data/lemke_tremblay4_5-14.dat
synple/data/lgquasi.dat
synple/data/li1.t
synple/data/li2.t
synple/data/mg1.t
synple/data/mg2.dat
synple/data/mg2.t
synple/data/n1.dat
synple/data/n1.t
synple/data/n2.t
synple/data/n2_32+10lev.dat
synple/data/n3.dat
synple/data/n4_34+14lev.dat
synple/data/n5.dat
synple/data/na1.t
synple/data/na2.t
synple/data/ne1_23+12lev.dat
synple/data/ne1_79lev-jK_c1.dat
synple/data/ne2.t
synple/data/ne2_138lev.dat
synple-1.0.3.dist-info/LICENSE
synple-1.0.3.dist-info/METADATA
synple-1.0.3.dist-info/WHEEL
synple-1.0.3.dist-info/top_level.txt
synple-1.0.3.dist-info/RECORD
